toxassign/Automation.py
toxassign/Format.py
toxassign/Match.py
toxassign/Merge.py
toxassign/PubChem.py
toxassign/Writer.py
toxassign/__init__.py
toxassign-0.5.7.dist-info/entry_points.txt
toxassign-0.5.7.dist-info/LICENSE
toxassign-0.5.7.dist-info/WHEEL
toxassign-0.5.7.dist-info/METADATA
toxassign-0.5.7.dist-info/RECORD
