Metadata-Version: 2.1
Name: toxassign
Version: 0.5.7
Summary: A toxic assigner used to classify potentially toxic chemicals from a list of formulas of compounds.
Home-page: https://github.com/swbreuer/ToxAssign
License: MIT
Author: Samuel Breuer
Author-email: swbreuer@mtu.edu
Maintainer: Samuel Breuer
Maintainer-email: swbreuer@mtu.edu
Requires-Python: >=3.9,<4.0
Classifier: License :: OSI Approved :: MIT License
Classifier: Operating System :: OS Independent
Classifier: Programming Language :: Python :: 3
Classifier: Programming Language :: Python :: 3.10
Classifier: Programming Language :: Python :: 3.9
Requires-Dist: openpyxl (>=3.0.9,<4.0.0)
Requires-Dist: pandas (>=1.3.5,<2.0.0)
Project-URL: Bug Tracker, https://github.com/swbreuer/ToxAssign/issues
Project-URL: Repository, https://github.com/swbreuer/ToxAssign
